{"clients_android_clash-meta.md":"C8HXmkMa","clients_android_readme.md":"c4o8DAeN","clients_android_v2rayng.md":"CYBvNWyZ","clients_ios_clash-mi.md":"C0t9Vnx_","clients_ios_readme.md":"B9RYaM_j","clients_ios_shadowrocket.md":"DTyZwT4G","clients_macos_clash-verge.md":"BvKtqkiq","clients_macos_readme.md":"BtHGNT-Z","clients_others_apple-tv.md":"BlEDleg8","clients_others_linux.md":"Ct5EgsEb","clients_others_readme.md":"Pk6mea7s","clients_others_router.md":"DcLFufQ1","clients_windows_clash-verge.md":"B1s_WguO","clients_windows_readme.md":"CVzFfK2v","clients_windows_v2rayn.md":"DyLvsmV6","deploy.md":"BzSY4QUA","download.md":"CPVCWGQW","guide_faq.md":"9w5-Op4K","guide_getting-started.md":"B0D5yAPD","guide_privacy.md":"BrAan5g8","guide_subscription.md":"Cyh_qpxh","index.md":"HdRnjMqU","links.md":"DWnuLzBN","policy_terms.md":"_5Pg_6hl","support.md":"BC2CFnJ_"}
